dataspace_sdk/__init__.py
dataspace_sdk/__version__.py
dataspace_sdk/auth.py
dataspace_sdk/base.py
dataspace_sdk/client.py
dataspace_sdk/exceptions.py
dataspace_sdk/resources/__init__.py
dataspace_sdk/resources/aimodels.py
dataspace_sdk/resources/auditors.py
dataspace_sdk/resources/datasets.py
dataspace_sdk/resources/sectors.py
dataspace_sdk/resources/usecases.py
dataspace_sdk-0.4.15.dist-info/METADATA
dataspace_sdk-0.4.15.dist-info/WHEEL
dataspace_sdk-0.4.15.dist-info/top_level.txt
dataspace_sdk-0.4.15.dist-info/RECORD
