Metadata-Version: 2.4
Name: dataspace-sdk
Version: 0.4.15
Summary: Python SDK for DataSpace API
Home-page: https://github.com/CivicDataLab/DataExchange
Author: CivicDataLab
Author-email: CivicDataLab <tech@civicdatalab.in>
License: AGPL-3.0
Project-URL: Homepage, https://github.com/CivicDataLab/DataExchange
Project-URL: Documentation, https://github.com/CivicDataLab/DataExchange/blob/main/docs/sdk/README.md
Project-URL: Repository, https://github.com/CivicDataLab/DataExchange
Project-URL: Bug Tracker, https://github.com/CivicDataLab/DataExchange/issues
Keywords: dataspace,api,sdk,datasets,aimodels,usecases
Classifier: Development Status :: 3 - Alpha
Classifier: Intended Audience :: Developers
Classifier: License :: OSI Approved :: GNU Affero General Public License v3
Classifier: Programming Language :: Python :: 3
Classifier: Programming Language :: Python :: 3.8
Classifier: Programming Language :: Python :: 3.9
Classifier: Programming Language :: Python :: 3.10
Classifier: Programming Language :: Python :: 3.11
Classifier: Programming Language :: Python :: 3.12
Requires-Python: >=3.8
Requires-Dist: requests>=2.28.0
Provides-Extra: dev
Requires-Dist: pytest>=7.0.0; extra == "dev"
Requires-Dist: pytest-cov>=4.0.0; extra == "dev"
Requires-Dist: black>=23.0.0; extra == "dev"
Requires-Dist: flake8>=6.0.0; extra == "dev"
Requires-Dist: mypy>=1.0.0; extra == "dev"
Requires-Dist: types-requests>=2.28.0; extra == "dev"
Dynamic: author
Dynamic: home-page
Dynamic: requires-python
